<?xml version = "1.0"?>

<students nillable="false">
    <student minOccurs="1">
        <firstname minLength="3" maxLength="10" nillable="false"></firstname>
        <lastname minLength="3" maxLength="10" nillable="false"></lastname>
        <nickname minLength="3" maxLength="10"></nickname>
        <email pattern="[a-z0-9]+@schoolname.org" nillable="false"></email>
        <age type="positiveInteger" min="9" max="19"></age>
        <contact>
            <phone length="10"></phone>
        </contact>
        <gender nillable="false" ></gender>
        <marks minOccurs="1" maxOccurs="1">
            <subject minOccurs="5" maxOccurs="6" >
                <name pattern="math|hindi|english|science|history"></name>
                <score type="positiveDecimal"></score>
            </subject>
        </marks>
    </student>
</students>